pybootstrapgui/__init__.py
pybootstrapgui/base.py
pybootstrapgui/bootstrap_builder.py
pybootstrapgui/components.py
pybootstrapgui/html_builder.py
pybootstrapgui/tag.py
pybootstrapgui/utils.py
pybootstrapgui/extensions/__init__.py
pybootstrapgui/extensions/html_comments.py
pybootstrapgui/extensions/jinja_components.py
pybootstrapgui/extensions/pywebview_utils.py
pybootstrapgui/prebuilt_components/__init__.py
pybootstrapgui/prebuilt_components/navbar.py
pybootstrapgui/static/css/bootstrap-icons.min.css
pybootstrapgui/static/css/bootstrap.min.css
pybootstrapgui/static/css/bootstrap.min.css.map
pybootstrapgui/static/css/fonts/bootstrap-icons.woff
pybootstrapgui/static/css/fonts/bootstrap-icons.woff2
pybootstrapgui/static/images/favicon.ico
pybootstrapgui/static/js/bootstrap.bundle.min.js
pybootstrapgui/static/js/bootstrap.bundle.min.js.map
pybootstrapgui-0.0.1.dist-info/licenses/LICENCE.txt
pybootstrapgui-0.0.1.dist-info/METADATA
pybootstrapgui-0.0.1.dist-info/WHEEL
pybootstrapgui-0.0.1.dist-info/top_level.txt
pybootstrapgui-0.0.1.dist-info/RECORD
