Metadata-Version: 2.4
Name: PyBootstrapGUI
Version: 0.0.1
Summary: Package to build bootstrap html
Author-email: Roman Smolnyk <poma23324@gmail.com>
Project-URL: Homepage, https://github.com/roman-smolnyk/python-pybootstrapgui
Keywords: bootstrap,html,builder,gui
Classifier: Programming Language :: Python :: 3
Classifier: License :: OSI Approved :: MIT License
Classifier: Operating System :: OS Independent
Requires-Python: >=3.8
License-File: LICENCE.txt
Dynamic: license-file
